{
	"configurations" : 
	[
		{
			"directories" : 
			[
				{
					"build" : ".",
					"jsonFile" : "directory-.-Debug-d0094a50bb2071803777.json",
					"minimumCMakeVersion" : 
					{
						"string" : "3.25"
					},
					"projectIndex" : 0,
					"source" : ".",
					"targetIndexes" : 
					[
						0
					]
				}
			],
			"name" : "Debug",
			"projects" : 
			[
				{
					"directoryIndexes" : 
					[
						0
					],
					"name" : "06_MergeList",
					"targetIndexes" : 
					[
						0
					]
				}
			],
			"targets" : 
			[
				{
					"directoryIndex" : 0,
					"id" : "MergeList::@6890427a1f51a3e7e1df",
					"jsonFile" : "target-MergeList-Debug-1471ea274a00848a2e2d.json",
					"name" : "MergeList",
					"projectIndex" : 0
				}
			]
		}
	],
	"kind" : "codemodel",
	"paths" : 
	{
		"build" : "D:/data/duotone/repo/02-Linear List/TextBook/06_MergeList/cmake-build-debug",
		"source" : "D:/data/duotone/repo/02-Linear List/TextBook/06_MergeList"
	},
	"version" : 
	{
		"major" : 2,
		"minor" : 4
	}
}
