{
	"configurations" : 
	[
		{
			"directories" : 
			[
				{
					"build" : ".",
					"jsonFile" : "directory-.-Debug-d0094a50bb2071803777.json",
					"minimumCMakeVersion" : 
					{
						"string" : "3.25"
					},
					"projectIndex" : 0,
					"source" : ".",
					"targetIndexes" : 
					[
						0
					]
				}
			],
			"name" : "Debug",
			"projects" : 
			[
				{
					"directoryIndexes" : 
					[
						0
					],
					"name" : "Exercise",
					"targetIndexes" : 
					[
						0
					]
				}
			],
			"targets" : 
			[
				{
					"directoryIndex" : 0,
					"id" : "CharacterFrequencyStatistics::@6890427a1f51a3e7e1df",
					"jsonFile" : "target-CharacterFrequencyStatistics-Debug-aff9c005d3db984f9fa9.json",
					"name" : "CharacterFrequencyStatistics",
					"projectIndex" : 0
				}
			]
		}
	],
	"kind" : "codemodel",
	"paths" : 
	{
		"build" : "D:/data/duotone/repo/04-String, Array and Generalized List/Exercise/cmake-build-debug",
		"source" : "D:/data/duotone/repo/04-String, Array and Generalized List/Exercise"
	},
	"version" : 
	{
		"major" : 2,
		"minor" : 4
	}
}
